{
  "kind": "collectionType",
  "collectionName": "projects",
  "info": {
    "singularName": "project",
    "pluralName": "projects",
    "displayName": "project"
  },
  "options": {
    "draftAndPublish": true
  },
  "pluginOptions": {},
  "attributes": {
    "title": {
      "type": "string"
    },
    "description": {
      "type": "richtext"
    },
    "media": {
      "allowedTypes": [
        "images",
        "files",
        "videos",
        "audios"
      ],
      "type": "media",
      "multiple": true
    },
    "status": {
      "type": "enumeration",
      "enum": [
        "ongoing",
        "completed",
        "upcoming"
      ]
    }
  }
}
